{
  "contract": "heating",
  "name": "Heating Oil",
  "date": "2026-07-01",
  "curve_months": [
    {
      "expiry": "2026-07",
      "price": 3.316800117492676
    },
    {
      "expiry": "2026-08",
      "price": 3.194700002670288
    },
    {
      "expiry": "2026-09",
      "price": 3.138700008392334
    },
    {
      "expiry": "2026-10",
      "price": 3.0864999294281006
    },
    {
      "expiry": "2026-11",
      "price": 3.0211000442504883
    },
    {
      "expiry": "2026-12",
      "price": 2.949399948120117
    },
    {
      "expiry": "2027-01",
      "price": 2.904599905014038
    },
    {
      "expiry": "2027-02",
      "price": 2.8661999702453613
    }
  ],
  "m1_price": 3.316800117492676,
  "m2_price": 3.194700002670288,
  "m3_price": 3.138700008392334,
  "m6_price": 2.949399948120117,
  "spread_m1m3": -5.3696,
  "spread_m1m6": -11.0769,
  "curve_slope_proxy": -0.9906,
  "signal": "BACKWARDATION",
  "source": "yfinance futures"
}