{
  "symbol": "DIA",
  "timestamp": "2026-06-18 14:44:19",
  "spot": 517.06,
  "total_gex": 332127505.94,
  "zero_gamma": 517.78,
  "call_wall": {
    "strike": 518.0,
    "gex": 122779977.57
  },
  "put_wall": {
    "strike": 518.0,
    "gex": -49520471.34
  },
  "levels": [
    {
      "strike": 185.0,
      "call_oi": 4.0,
      "put_oi": 662.0,
      "call_gex": 49.35,
      "put_gex": -14208.43,
      "net_gex": -14159.08
    },
    {
      "strike": 190.0,
      "call_oi": 25.0,
      "put_oi": 1825.0,
      "call_gex": 626.58,
      "put_gex": -11116.65,
      "net_gex": -10490.07
    },
    {
      "strike": 195.0,
      "call_oi": 6.0,
      "put_oi": 479.0,
      "call_gex": 136.25,
      "put_gex": -12806.11,
      "net_gex": -12669.86
    },
    {
      "strike": 200.0,
      "call_oi": 2.0,
      "put_oi": 349.0,
      "call_gex": 53.47,
      "put_gex": -9330.55,
      "net_gex": -9277.08
    },
    {
      "strike": 205.0,
      "call_oi": 1.0,
      "put_oi": 3.0,
      "call_gex": 26.74,
      "put_gex": -80.21,
      "net_gex": -53.47
    },
    {
      "strike": 210.0,
      "call_oi": 9.0,
      "put_oi": 270.0,
      "call_gex": 240.62,
      "put_gex": -7218.48,
      "net_gex": -6977.86
    },
    {
      "strike": 215.0,
      "call_oi": 8.0,
      "put_oi": 259.0,
      "call_gex": 427.76,
      "put_gex": -7004.6,
      "net_gex": -6576.84
    },
    {
      "strike": 220.0,
      "call_oi": 29.0,
      "put_oi": 142.0,
      "call_gex": 1149.61,
      "put_gex": -3903.33,
      "net_gex": -2753.72
    },
    {
      "strike": 225.0,
      "call_oi": 0.0,
      "put_oi": 36.0,
      "call_gex": 0.0,
      "put_gex": -1015.93,
      "net_gex": -1015.93
    },
    {
      "strike": 230.0,
      "call_oi": 23.0,
      "put_oi": 161.0,
      "call_gex": 668.38,
      "put_gex": -4892.52,
      "net_gex": -4224.15
    },
    {
      "strike": 235.0,
      "call_oi": 25.0,
      "put_oi": 275.0,
      "call_gex": 828.79,
      "put_gex": -7913.59,
      "net_gex": -7084.8
    },
    {
      "strike": 240.0,
      "call_oi": 13.0,
      "put_oi": 1082.0,
      "call_gex": 374.29,
      "put_gex": -29462.09,
      "net_gex": -29087.79
    },
    {
      "strike": 245.0,
      "call_oi": 6.0,
      "put_oi": 106.0,
      "call_gex": 160.41,
      "put_gex": -2887.39,
      "net_gex": -2726.98
    },
    {
      "strike": 250.0,
      "call_oi": 30.0,
      "put_oi": 2568.0,
      "call_gex": 1470.43,
      "put_gex": -75392.99,
      "net_gex": -73922.56
    },
    {
      "strike": 255.0,
      "call_oi": 21.0,
      "put_oi": 40.0,
      "call_gex": 1122.87,
      "put_gex": -1604.11,
      "net_gex": -481.23
    },
    {
      "strike": 260.0,
      "call_oi": 29.0,
      "put_oi": 75.0,
      "call_gex": 882.26,
      "put_gex": -4250.88,
      "net_gex": -3368.62
    },
    {
      "strike": 265.0,
      "call_oi": 18.0,
      "put_oi": 107.0,
      "call_gex": 962.46,
      "put_gex": -6603.57,
      "net_gex": -5641.11
    },
    {
      "strike": 270.0,
      "call_oi": 11.0,
      "put_oi": 171.0,
      "call_gex": 588.17,
      "put_gex": -9330.55,
      "net_gex": -8742.38
    },
    {
      "strike": 275.0,
      "call_oi": 4.0,
      "put_oi": 269.0,
      "call_gex": 213.88,
      "put_gex": -14410.22,
      "net_gex": -14196.34
    },
    {
      "strike": 280.0,
      "call_oi": 165.0,
      "put_oi": 214.0,
      "call_gex": 16682.71,
      "put_gex": -11709.98,
      "net_gex": 4972.73
    },
    {
      "strike": 285.0,
      "call_oi": 7.0,
      "put_oi": 715.0,
      "call_gex": 401.03,
      "put_gex": -38418.34,
      "net_gex": -38017.32
    },
    {
      "strike": 290.0,
      "call_oi": 38.0,
      "put_oi": 1321.0,
      "call_gex": 2914.13,
      "put_gex": -80927.16,
      "net_gex": -78013.03
    },
    {
      "strike": 295.0,
      "call_oi": 4.0,
      "put_oi": 912.0,
      "call_gex": 347.56,
      "put_gex": -87931.76,
      "net_gex": -87584.2
    },
    {
      "strike": 300.0,
      "call_oi": 56.0,
      "put_oi": 1109.0,
      "call_gex": 5133.14,
      "put_gex": -89268.51,
      "net_gex": -84135.37
    },
    {
      "strike": 305.0,
      "call_oi": 23.0,
      "put_oi": 162.0,
      "call_gex": 2112.07,
      "put_gex": -12512.03,
      "net_gex": -10399.96
    },
    {
      "strike": 310.0,
      "call_oi": 85.0,
      "put_oi": 950.0,
      "call_gex": 10319.75,
      "put_gex": -77585.27,
      "net_gex": -67265.52
    },
    {
      "strike": 315.0,
      "call_oi": 44.0,
      "put_oi": 1149.0,
      "call_gex": 5587.64,
      "put_gex": -56116.58,
      "net_gex": -50528.94
    },
    {
      "strike": 320.0,
      "call_oi": 17.0,
      "put_oi": 1709.0,
      "call_gex": 2245.75,
      "put_gex": -128989.22,
      "net_gex": -126743.47
    },
    {
      "strike": 325.0,
      "call_oi": 193.0,
      "put_oi": 4688.0,
      "call_gex": 20692.97,
      "put_gex": -392356.02,
      "net_gex": -371663.05
    },
    {
      "strike": 330.0,
      "call_oi": 12.0,
      "put_oi": 2901.0,
      "call_gex": 1577.37,
      "put_gex": -328515.32,
      "net_gex": -326937.95
    },
    {
      "strike": 335.0,
      "call_oi": 12.0,
      "put_oi": 3437.0,
      "call_gex": 1764.52,
      "put_gex": -277263.21,
      "net_gex": -275498.7
    },
    {
      "strike": 340.0,
      "call_oi": 171.0,
      "put_oi": 1914.0,
      "call_gex": 24542.83,
      "put_gex": -182459.73,
      "net_gex": -157916.9
    },
    {
      "strike": 345.0,
      "call_oi": 17.0,
      "put_oi": 741.0,
      "call_gex": 2807.19,
      "put_gex": -75249.97,
      "net_gex": -72442.79
    },
    {
      "strike": 350.0,
      "call_oi": 945.0,
      "put_oi": 4272.0,
      "call_gex": 152042.54,
      "put_gex": -653651.78,
      "net_gex": -501609.24
    },
    {
      "strike": 355.0,
      "call_oi": 29.0,
      "put_oi": 922.0,
      "call_gex": 5266.82,
      "put_gex": -106190.53,
      "net_gex": -100923.71
    },
    {
      "strike": 360.0,
      "call_oi": 618.0,
      "put_oi": 3229.0,
      "call_gex": 116270.97,
      "put_gex": -269917.45,
      "net_gex": -153646.48
    },
    {
      "strike": 365.0,
      "call_oi": 204.0,
      "put_oi": 1477.0,
      "call_gex": 41920.64,
      "put_gex": -204260.75,
      "net_gex": -162340.11
    },
    {
      "strike": 370.0,
      "call_oi": 177.0,
      "put_oi": 3382.0,
      "call_gex": 39273.87,
      "put_gex": -681290.55,
      "net_gex": -642016.68
    },
    {
      "strike": 375.0,
      "call_oi": 1375.0,
      "put_oi": 2494.0,
      "call_gex": 190960.04,
      "put_gex": -480290.3,
      "net_gex": -289330.26
    },
    {
      "strike": 380.0,
      "call_oi": 308.0,
      "put_oi": 5613.0,
      "call_gex": 80927.16,
      "put_gex": -1439016.3,
      "net_gex": -1358089.14
    },
    {
      "strike": 385.0,
      "call_oi": 72.0,
      "put_oi": 2264.0,
      "call_gex": 17620.48,
      "put_gex": -516311.73,
      "net_gex": -498691.25
    },
    {
      "strike": 390.0,
      "call_oi": 239.0,
      "put_oi": 3910.0,
      "call_gex": 72318.46,
      "put_gex": -1002259.1,
      "net_gex": -929940.64
    },
    {
      "strike": 395.0,
      "call_oi": 74.0,
      "put_oi": 4144.0,
      "call_gex": 23847.71,
      "put_gex": -614131.0,
      "net_gex": -590283.28
    },
    {
      "strike": 396.0,
      "call_oi": 0.0,
      "put_oi": 1120.0,
      "call_gex": 0.0,
      "put_gex": -30712.15,
      "net_gex": -30712.15
    },
    {
      "strike": 397.0,
      "call_oi": 0.0,
      "put_oi": 2442.0,
      "call_gex": 0.0,
      "put_gex": -68069.49,
      "net_gex": -68069.49
    },
    {
      "strike": 398.0,
      "call_oi": 0.0,
      "put_oi": 1787.0,
      "call_gex": 0.0,
      "put_gex": -50633.22,
      "net_gex": -50633.22
    },
    {
      "strike": 399.0,
      "call_oi": 0.0,
      "put_oi": 2354.0,
      "call_gex": 0.0,
      "put_gex": -67797.11,
      "net_gex": -67797.11
    },
    {
      "strike": 400.0,
      "call_oi": 479.0,
      "put_oi": 10712.0,
      "call_gex": 156104.04,
      "put_gex": -3170414.0,
      "net_gex": -3014309.96
    },
    {
      "strike": 401.0,
      "call_oi": 0.0,
      "put_oi": 3529.0,
      "call_gex": 0.0,
      "put_gex": -105005.62,
      "net_gex": -105005.62
    },
    {
      "strike": 402.0,
      "call_oi": 0.0,
      "put_oi": 1114.0,
      "call_gex": 0.0,
      "put_gex": -33741.62,
      "net_gex": -33741.62
    },
    {
      "strike": 403.0,
      "call_oi": 0.0,
      "put_oi": 491.0,
      "call_gex": 0.0,
      "put_gex": -15115.39,
      "net_gex": -15115.39
    },
    {
      "strike": 404.0,
      "call_oi": 0.0,
      "put_oi": 1057.0,
      "call_gex": 0.0,
      "put_gex": -33224.59,
      "net_gex": -33224.59
    },
    {
      "strike": 405.0,
      "call_oi": 313.0,
      "put_oi": 4356.0,
      "call_gex": 115228.3,
      "put_gex": -548039.31,
      "net_gex": -432811.01
    },
    {
      "strike": 406.0,
      "call_oi": 0.0,
      "put_oi": 682.0,
      "call_gex": 0.0,
      "put_gex": -18233.34,
      "net_gex": -18233.34
    },
    {
      "strike": 407.0,
      "call_oi": 0.0,
      "put_oi": 914.0,
      "call_gex": 0.0,
      "put_gex": -24435.89,
      "net_gex": -24435.89
    },
    {
      "strike": 408.0,
      "call_oi": 0.0,
      "put_oi": 496.0,
      "call_gex": 0.0,
      "put_gex": -13260.61,
      "net_gex": -13260.61
    },
    {
      "strike": 409.0,
      "call_oi": 0.0,
      "put_oi": 1206.0,
      "call_gex": 0.0,
      "put_gex": -32242.54,
      "net_gex": -32242.54
    },
    {
      "strike": 410.0,
      "call_oi": 212.0,
      "put_oi": 7021.0,
      "call_gex": 80232.05,
      "put_gex": -1730376.16,
      "net_gex": -1650144.11
    },
    {
      "strike": 411.0,
      "call_oi": 0.0,
      "put_oi": 393.0,
      "call_gex": 0.0,
      "put_gex": -10506.9,
      "net_gex": -10506.9
    },
    {
      "strike": 412.0,
      "call_oi": 0.0,
      "put_oi": 3295.0,
      "call_gex": 0.0,
      "put_gex": -93305.51,
      "net_gex": -93305.51
    },
    {
      "strike": 413.0,
      "call_oi": 0.0,
      "put_oi": 713.0,
      "call_gex": 0.0,
      "put_gex": -24275.47,
      "net_gex": -24275.47
    },
    {
      "strike": 414.0,
      "call_oi": 0.0,
      "put_oi": 396.0,
      "call_gex": 0.0,
      "put_gex": -12725.91,
      "net_gex": -12725.91
    },
    {
      "strike": 415.0,
      "call_oi": 92.0,
      "put_oi": 5510.0,
      "call_gex": 37856.91,
      "put_gex": -2023982.72,
      "net_gex": -1986125.82
    },
    {
      "strike": 416.0,
      "call_oi": 0.0,
      "put_oi": 2973.0,
      "call_gex": 0.0,
      "put_gex": -414581.26,
      "net_gex": -414581.26
    },
    {
      "strike": 417.0,
      "call_oi": 0.0,
      "put_oi": 2339.0,
      "call_gex": 0.0,
      "put_gex": -217730.69,
      "net_gex": -217730.69
    },
    {
      "strike": 418.0,
      "call_oi": 0.0,
      "put_oi": 1573.0,
      "call_gex": 0.0,
      "put_gex": -235643.21,
      "net_gex": -235643.21
    },
    {
      "strike": 419.0,
      "call_oi": 0.0,
      "put_oi": 1503.0,
      "call_gex": 0.0,
      "put_gex": -423243.44,
      "net_gex": -423243.44
    },
    {
      "strike": 420.0,
      "call_oi": 1686.0,
      "put_oi": 9809.0,
      "call_gex": 764837.87,
      "put_gex": -3488119.18,
      "net_gex": -2723281.32
    },
    {
      "strike": 421.0,
      "call_oi": 1.0,
      "put_oi": 1746.0,
      "call_gex": 401.03,
      "put_gex": -458961.54,
      "net_gex": -458560.51
    },
    {
      "strike": 422.0,
      "call_oi": 0.0,
      "put_oi": 2551.0,
      "call_gex": 0.0,
      "put_gex": -858785.02,
      "net_gex": -858785.02
    },
    {
      "strike": 423.0,
      "call_oi": 0.0,
      "put_oi": 2054.0,
      "call_gex": 0.0,
      "put_gex": -664073.26,
      "net_gex": -664073.26
    },
    {
      "strike": 424.0,
      "call_oi": 0.0,
      "put_oi": 3514.0,
      "call_gex": 0.0,
      "put_gex": -701823.22,
      "net_gex": -701823.22
    },
    {
      "strike": 425.0,
      "call_oi": 652.0,
      "put_oi": 4115.0,
      "call_gex": 295904.14,
      "put_gex": -1593545.9,
      "net_gex": -1297641.76
    },
    {
      "strike": 426.0,
      "call_oi": 0.0,
      "put_oi": 1924.0,
      "call_gex": 0.0,
      "put_gex": -520933.51,
      "net_gex": -520933.51
    },
    {
      "strike": 427.0,
      "call_oi": 3.0,
      "put_oi": 1549.0,
      "call_gex": 1363.49,
      "put_gex": -381376.26,
      "net_gex": -380012.77
    },
    {
      "strike": 428.0,
      "call_oi": 0.0,
      "put_oi": 1616.0,
      "call_gex": 0.0,
      "put_gex": -586835.54,
      "net_gex": -586835.54
    },
    {
      "strike": 429.0,
      "call_oi": 1.0,
      "put_oi": 1351.0,
      "call_gex": 534.7,
      "put_gex": -478237.55,
      "net_gex": -477702.84
    },
    {
      "strike": 430.0,
      "call_oi": 826.0,
      "put_oi": 10979.0,
      "call_gex": 424580.19,
      "put_gex": -4737300.08,
      "net_gex": -4312719.89
    },
    {
      "strike": 431.0,
      "call_oi": 0.0,
      "put_oi": 1919.0,
      "call_gex": 0.0,
      "put_gex": -831087.45,
      "net_gex": -831087.45
    },
    {
      "strike": 432.0,
      "call_oi": 6.0,
      "put_oi": 1319.0,
      "call_gex": 3101.27,
      "put_gex": -581889.55,
      "net_gex": -578788.27
    },
    {
      "strike": 433.0,
      "call_oi": 0.0,
      "put_oi": 1130.0,
      "call_gex": 0.0,
      "put_gex": -400705.74,
      "net_gex": -400705.74
    },
    {
      "strike": 434.0,
      "call_oi": 2.0,
      "put_oi": 2636.0,
      "call_gex": 1069.4,
      "put_gex": -1050689.6,
      "net_gex": -1049620.2
    },
    {
      "strike": 435.0,
      "call_oi": 354.0,
      "put_oi": 4360.0,
      "call_gex": 203694.76,
      "put_gex": -1782001.65,
      "net_gex": -1578306.89
    },
    {
      "strike": 436.0,
      "call_oi": 1.0,
      "put_oi": 2146.0,
      "call_gex": 534.7,
      "put_gex": -956555.3,
      "net_gex": -956020.6
    },
    {
      "strike": 437.0,
      "call_oi": 5.0,
      "put_oi": 1373.0,
      "call_gex": 2807.19,
      "put_gex": -439792.47,
      "net_gex": -436985.28
    },
    {
      "strike": 438.0,
      "call_oi": 1.0,
      "put_oi": 1679.0,
      "call_gex": 614.91,
      "put_gex": -724334.18,
      "net_gex": -723719.28
    },
    {
      "strike": 439.0,
      "call_oi": 0.0,
      "put_oi": 1523.0,
      "call_gex": 0.0,
      "put_gex": -716581.0,
      "net_gex": -716581.0
    },
    {
      "strike": 440.0,
      "call_oi": 370.0,
      "put_oi": 11259.0,
      "call_gex": 193027.45,
      "put_gex": -6068173.58,
      "net_gex": -5875146.12
    },
    {
      "strike": 441.0,
      "call_oi": 1.0,
      "put_oi": 2151.0,
      "call_gex": 641.64,
      "put_gex": -626483.7,
      "net_gex": -625842.06
    },
    {
      "strike": 442.0,
      "call_oi": 0.0,
      "put_oi": 1448.0,
      "call_gex": 0.0,
      "put_gex": -696770.29,
      "net_gex": -696770.29
    },
    {
      "strike": 443.0,
      "call_oi": 1.0,
      "put_oi": 1208.0,
      "call_gex": 641.64,
      "put_gex": -713346.05,
      "net_gex": -712704.41
    },
    {
      "strike": 444.0,
      "call_oi": 2.0,
      "put_oi": 1754.0,
      "call_gex": 1310.02,
      "put_gex": -929739.99,
      "net_gex": -928429.97
    },
    {
      "strike": 445.0,
      "call_oi": 464.0,
      "put_oi": 8633.0,
      "call_gex": 291439.37,
      "put_gex": -5441770.08,
      "net_gex": -5150330.71
    },
    {
      "strike": 446.0,
      "call_oi": 0.0,
      "put_oi": 2019.0,
      "call_gex": 0.0,
      "put_gex": -994198.33,
      "net_gex": -994198.33
    },
    {
      "strike": 447.0,
      "call_oi": 0.0,
      "put_oi": 1676.0,
      "call_gex": 0.0,
      "put_gex": -703561.01,
      "net_gex": -703561.01
    },
    {
      "strike": 448.0,
      "call_oi": 0.0,
      "put_oi": 1087.0,
      "call_gex": 0.0,
      "put_gex": -648165.87,
      "net_gex": -648165.87
    },
    {
      "strike": 449.0,
      "call_oi": 0.0,
      "put_oi": 1190.0,
      "call_gex": 0.0,
      "put_gex": -549406.39,
      "net_gex": -549406.39
    },
    {
      "strike": 450.0,
      "call_oi": 3539.0,
      "put_oi": 10234.0,
      "call_gex": 2410303.33,
      "put_gex": -6728450.45,
      "net_gex": -4318147.12
    },
    {
      "strike": 451.0,
      "call_oi": 13.0,
      "put_oi": 1545.0,
      "call_gex": 9731.58,
      "put_gex": -669634.16,
      "net_gex": -659902.58
    },
    {
      "strike": 452.0,
      "call_oi": 0.0,
      "put_oi": 1404.0,
      "call_gex": 0.0,
      "put_gex": -876537.13,
      "net_gex": -876537.13
    },
    {
      "strike": 453.0,
      "call_oi": 0.0,
      "put_oi": 1040.0,
      "call_gex": 0.0,
      "put_gex": -493663.7,
      "net_gex": -493663.7
    },
    {
      "strike": 454.0,
      "call_oi": 1.0,
      "put_oi": 942.0,
      "call_gex": 802.05,
      "put_gex": -695460.27,
      "net_gex": -694658.22
    },
    {
      "strike": 455.0,
      "call_oi": 1034.0,
      "put_oi": 3605.0,
      "call_gex": 768286.69,
      "put_gex": -2566917.57,
      "net_gex": -1798630.88
    },
    {
      "strike": 456.0,
      "call_oi": 3.0,
      "put_oi": 960.0,
      "call_gex": 2486.36,
      "put_gex": -716821.62,
      "net_gex": -714335.25
    },
    {
      "strike": 457.0,
      "call_oi": 24.0,
      "put_oi": 992.0,
      "call_gex": 20532.56,
      "put_gex": -698401.13,
      "net_gex": -677868.57
    },
    {
      "strike": 458.0,
      "call_oi": 5.0,
      "put_oi": 790.0,
      "call_gex": 4304.35,
      "put_gex": -410490.79,
      "net_gex": -406186.44
    },
    {
      "strike": 459.0,
      "call_oi": 1.0,
      "put_oi": 740.0,
      "call_gex": 882.26,
      "put_gex": -532803.89,
      "net_gex": -531921.64
    },
    {
      "strike": 460.0,
      "call_oi": 2481.0,
      "put_oi": 15059.0,
      "call_gex": 1896240.75,
      "put_gex": -11531117.86,
      "net_gex": -9634877.11
    },
    {
      "strike": 461.0,
      "call_oi": 74.0,
      "put_oi": 941.0,
      "call_gex": 69243.92,
      "put_gex": -642310.88,
      "net_gex": -573066.96
    },
    {
      "strike": 462.0,
      "call_oi": 22.0,
      "put_oi": 802.0,
      "call_gex": 21174.2,
      "put_gex": -600523.91,
      "net_gex": -579349.71
    },
    {
      "strike": 463.0,
      "call_oi": 27.0,
      "put_oi": 972.0,
      "call_gex": 25879.58,
      "put_gex": -771895.93,
      "net_gex": -746016.35
    },
    {
      "strike": 464.0,
      "call_oi": 11.0,
      "put_oi": 337.0,
      "call_gex": 10881.19,
      "put_gex": -245000.5,
      "net_gex": -234119.31
    },
    {
      "strike": 465.0,
      "call_oi": 926.0,
      "put_oi": 3535.0,
      "call_gex": 785129.81,
      "put_gex": -2224895.38,
      "net_gex": -1439765.58
    },
    {
      "strike": 466.0,
      "call_oi": 18.0,
      "put_oi": 577.0,
      "call_gex": 18019.46,
      "put_gex": -536573.54,
      "net_gex": -518554.08
    },
    {
      "strike": 467.0,
      "call_oi": 0.0,
      "put_oi": 524.0,
      "call_gex": 0.0,
      "put_gex": -518955.11,
      "net_gex": -518955.11
    },
    {
      "strike": 468.0,
      "call_oi": 177.0,
      "put_oi": 527.0,
      "call_gex": 194016.65,
      "put_gex": -456448.44,
      "net_gex": -262431.78
    },
    {
      "strike": 469.0,
      "call_oi": 4.0,
      "put_oi": 634.0,
      "call_gex": 4357.82,
      "put_gex": -648165.87,
      "net_gex": -643808.05
    },
    {
      "strike": 470.0,
      "call_oi": 3883.0,
      "put_oi": 7725.0,
      "call_gex": 3933776.52,
      "put_gex": -6756228.22,
      "net_gex": -2822451.7
    },
    {
      "strike": 471.0,
      "call_oi": 43.0,
      "put_oi": 353.0,
      "call_gex": 48283.6,
      "put_gex": -298417.23,
      "net_gex": -250133.64
    },
    {
      "strike": 472.0,
      "call_oi": 39.0,
      "put_oi": 348.0,
      "call_gex": 45342.74,
      "put_gex": -325152.34,
      "net_gex": -279809.6
    },
    {
      "strike": 473.0,
      "call_oi": 2.0,
      "put_oi": 671.0,
      "call_gex": 2459.63,
      "put_gex": -480002.06,
      "net_gex": -477542.43
    },
    {
      "strike": 474.0,
      "call_oi": 13.0,
      "put_oi": 145.0,
      "call_gex": 9517.7,
      "put_gex": -148353.09,
      "net_gex": -138835.4
    },
    {
      "strike": 475.0,
      "call_oi": 3602.0,
      "put_oi": 6841.0,
      "call_gex": 4004223.52,
      "put_gex": -7019381.86,
      "net_gex": -3015158.33
    },
    {
      "strike": 476.0,
      "call_oi": 8.0,
      "put_oi": 586.0,
      "call_gex": 7271.95,
      "put_gex": -587824.74,
      "net_gex": -580552.79
    },
    {
      "strike": 477.0,
      "call_oi": 396.0,
      "put_oi": 471.0,
      "call_gex": 524302.13,
      "put_gex": -525130.92,
      "net_gex": -828.79
    },
    {
      "strike": 478.0,
      "call_oi": 21.0,
      "put_oi": 318.0,
      "call_gex": 20078.06,
      "put_gex": -320420.23,
      "net_gex": -300342.16
    },
    {
      "strike": 479.0,
      "call_oi": 46.0,
      "put_oi": 151.0,
      "call_gex": 57052.71,
      "put_gex": -148807.59,
      "net_gex": -91754.88
    },
    {
      "strike": 480.0,
      "call_oi": 1700.0,
      "put_oi": 15812.0,
      "call_gex": 1961955.63,
      "put_gex": -18052932.69,
      "net_gex": -16090977.06
    },
    {
      "strike": 481.0,
      "call_oi": 47.0,
      "put_oi": 331.0,
      "call_gex": 64886.1,
      "put_gex": -381910.97,
      "net_gex": -317024.87
    },
    {
      "strike": 482.0,
      "call_oi": 9.0,
      "put_oi": 730.0,
      "call_gex": 9891.99,
      "put_gex": -755587.52,
      "net_gex": -745695.53
    },
    {
      "strike": 483.0,
      "call_oi": 123.0,
      "put_oi": 215.0,
      "call_gex": 180461.95,
      "put_gex": -215725.56,
      "net_gex": -35263.6
    },
    {
      "strike": 484.0,
      "call_oi": 7.0,
      "put_oi": 222.0,
      "call_gex": 8421.56,
      "put_gex": -216420.67,
      "net_gex": -207999.11
    },
    {
      "strike": 485.0,
      "call_oi": 1676.0,
      "put_oi": 3471.0,
      "call_gex": 2148727.07,
      "put_gex": -5285744.01,
      "net_gex": -3137016.94
    },
    {
      "strike": 486.0,
      "call_oi": 26.0,
      "put_oi": 422.0,
      "call_gex": 36894.44,
      "put_gex": -578547.66,
      "net_gex": -541653.21
    },
    {
      "strike": 487.0,
      "call_oi": 19.0,
      "put_oi": 485.0,
      "call_gex": 27136.13,
      "put_gex": -707918.83,
      "net_gex": -680782.7
    },
    {
      "strike": 487.5,
      "call_oi": 4.0,
      "put_oi": 115.0,
      "call_gex": 5988.66,
      "put_gex": -165490.3,
      "net_gex": -159501.63
    },
    {
      "strike": 488.0,
      "call_oi": 48.0,
      "put_oi": 140.0,
      "call_gex": 74885.03,
      "put_gex": -207143.59,
      "net_gex": -132258.56
    },
    {
      "strike": 489.0,
      "call_oi": 16.0,
      "put_oi": 89.0,
      "call_gex": 22992.19,
      "put_gex": -143727.92,
      "net_gex": -120735.73
    },
    {
      "strike": 490.0,
      "call_oi": 3194.0,
      "put_oi": 12025.0,
      "call_gex": 3934792.45,
      "put_gex": -16889126.86,
      "net_gex": -12954334.41
    },
    {
      "strike": 491.0,
      "call_oi": 21.0,
      "put_oi": 213.0,
      "call_gex": 37696.5,
      "put_gex": -364078.65,
      "net_gex": -326382.15
    },
    {
      "strike": 492.0,
      "call_oi": 195.0,
      "put_oi": 1213.0,
      "call_gex": 395465.66,
      "put_gex": -1218773.2,
      "net_gex": -823307.54
    },
    {
      "strike": 492.5,
      "call_oi": 1.0,
      "put_oi": 23.0,
      "call_gex": 2112.07,
      "put_gex": -39033.25,
      "net_gex": -36921.18
    },
    {
      "strike": 493.0,
      "call_oi": 208.0,
      "put_oi": 274.0,
      "call_gex": 454229.42,
      "put_gex": -306170.42,
      "net_gex": 148059.01
    },
    {
      "strike": 494.0,
      "call_oi": 41.0,
      "put_oi": 670.0,
      "call_gex": 82370.86,
      "put_gex": -513608.09,
      "net_gex": -431237.23
    },
    {
      "strike": 495.0,
      "call_oi": 2225.0,
      "put_oi": 7804.0,
      "call_gex": 4973825.55,
      "put_gex": -11596511.93,
      "net_gex": -6622686.38
    },
    {
      "strike": 496.0,
      "call_oi": 55.0,
      "put_oi": 238.0,
      "call_gex": 95150.24,
      "put_gex": -300957.07,
      "net_gex": -205806.83
    },
    {
      "strike": 497.0,
      "call_oi": 59.0,
      "put_oi": 411.0,
      "call_gex": 151026.6,
      "put_gex": -198187.33,
      "net_gex": -47160.72
    },
    {
      "strike": 497.5,
      "call_oi": 2.0,
      "put_oi": 318.0,
      "call_gex": 5881.72,
      "put_gex": -825686.96,
      "net_gex": -819805.24
    },
    {
      "strike": 498.0,
      "call_oi": 40.0,
      "put_oi": 1416.0,
      "call_gex": 100203.17,
      "put_gex": -544326.72,
      "net_gex": -444123.55
    },
    {
      "strike": 499.0,
      "call_oi": 30.0,
      "put_oi": 1350.0,
      "call_gex": 75713.82,
      "put_gex": -3635038.46,
      "net_gex": -3559324.65
    },
    {
      "strike": 500.0,
      "call_oi": 9898.0,
      "put_oi": 11210.0,
      "call_gex": 19634822.08,
      "put_gex": -24618726.76,
      "net_gex": -4983904.68
    },
    {
      "strike": 501.0,
      "call_oi": 222.0,
      "put_oi": 304.0,
      "call_gex": 633194.21,
      "put_gex": -344348.14,
      "net_gex": 288846.07
    },
    {
      "strike": 502.0,
      "call_oi": 554.0,
      "put_oi": 1356.0,
      "call_gex": 1327825.69,
      "put_gex": -4135412.68,
      "net_gex": -2807586.98
    },
    {
      "strike": 502.5,
      "call_oi": 56.0,
      "put_oi": 343.0,
      "call_gex": 227328.59,
      "put_gex": -1402951.34,
      "net_gex": -1175622.74
    },
    {
      "strike": 503.0,
      "call_oi": 191.0,
      "put_oi": 558.0,
      "call_gex": 591968.68,
      "put_gex": -971232.87,
      "net_gex": -379264.19
    },
    {
      "strike": 504.0,
      "call_oi": 146.0,
      "put_oi": 499.0,
      "call_gex": 640492.9,
      "put_gex": -870441.53,
      "net_gex": -229948.63
    },
    {
      "strike": 505.0,
      "call_oi": 2728.0,
      "put_oi": 3751.0,
      "call_gex": 8924578.86,
      "put_gex": -10534032.14,
      "net_gex": -1609453.28
    },
    {
      "strike": 506.0,
      "call_oi": 153.0,
      "put_oi": 786.0,
      "call_gex": 632552.57,
      "put_gex": -2366030.0,
      "net_gex": -1733477.43
    },
    {
      "strike": 507.0,
      "call_oi": 305.0,
      "put_oi": 821.0,
      "call_gex": 1086915.67,
      "put_gex": -1647123.04,
      "net_gex": -560207.38
    },
    {
      "strike": 507.5,
      "call_oi": 24.0,
      "put_oi": 124.0,
      "call_gex": 137792.73,
      "put_gex": -730884.28,
      "net_gex": -593091.56
    },
    {
      "strike": 508.0,
      "call_oi": 244.0,
      "put_oi": 2867.0,
      "call_gex": 1175809.89,
      "put_gex": -6108035.62,
      "net_gex": -4932225.73
    },
    {
      "strike": 509.0,
      "call_oi": 136.0,
      "put_oi": 493.0,
      "call_gex": 744332.04,
      "put_gex": -2369559.03,
      "net_gex": -1625226.99
    },
    {
      "strike": 510.0,
      "call_oi": 6661.0,
      "put_oi": 6892.0,
      "call_gex": 23913321.04,
      "put_gex": -26176287.21,
      "net_gex": -2262966.17
    },
    {
      "strike": 511.0,
      "call_oi": 628.0,
      "put_oi": 453.0,
      "call_gex": 3821997.05,
      "put_gex": -3297427.57,
      "net_gex": 524569.48
    },
    {
      "strike": 512.0,
      "call_oi": 290.0,
      "put_oi": 720.0,
      "call_gex": 2133862.35,
      "put_gex": -6609960.47,
      "net_gex": -4476098.11
    },
    {
      "strike": 512.5,
      "call_oi": 75.0,
      "put_oi": 35.0,
      "call_gex": 476660.18,
      "put_gex": -205272.13,
      "net_gex": 271388.04
    },
    {
      "strike": 513.0,
      "call_oi": 600.0,
      "put_oi": 1306.0,
      "call_gex": 6819189.39,
      "put_gex": -15136988.33,
      "net_gex": -8317798.93
    },
    {
      "strike": 514.0,
      "call_oi": 694.0,
      "put_oi": 517.0,
      "call_gex": 8746469.6,
      "put_gex": -6798015.19,
      "net_gex": 1948454.41
    },
    {
      "strike": 515.0,
      "call_oi": 7422.0,
      "put_oi": 3811.0,
      "call_gex": 95846792.83,
      "put_gex": -40978552.03,
      "net_gex": 54868240.8
    },
    {
      "strike": 516.0,
      "call_oi": 3340.0,
      "put_oi": 974.0,
      "call_gex": 104085161.76,
      "put_gex": -17517107.73,
      "net_gex": 86568054.04
    },
    {
      "strike": 517.0,
      "call_oi": 1061.0,
      "put_oi": 1084.0,
      "call_gex": 17163776.59,
      "put_gex": -30538226.43,
      "net_gex": -13374449.84
    },
    {
      "strike": 517.5,
      "call_oi": 186.0,
      "put_oi": 151.0,
      "call_gex": 1393353.43,
      "put_gex": -1409127.15,
      "net_gex": -15773.71
    },
    {
      "strike": 518.0,
      "call_oi": 3860.0,
      "put_oi": 1599.0,
      "call_gex": 122779977.57,
      "put_gex": -49520471.34,
      "net_gex": 73259506.23
    },
    {
      "strike": 519.0,
      "call_oi": 1388.0,
      "put_oi": 658.0,
      "call_gex": 29341616.62,
      "put_gex": -15583464.57,
      "net_gex": 13758152.05
    },
    {
      "strike": 520.0,
      "call_oi": 11663.0,
      "put_oi": 7856.0,
      "call_gex": 105699855.13,
      "put_gex": -41200159.31,
      "net_gex": 64499695.82
    },
    {
      "strike": 521.0,
      "call_oi": 1963.0,
      "put_oi": 854.0,
      "call_gex": 27417838.72,
      "put_gex": -10223049.41,
      "net_gex": 17194789.31
    },
    {
      "strike": 522.0,
      "call_oi": 1776.0,
      "put_oi": 1439.0,
      "call_gex": 16591538.41,
      "put_gex": -13799858.82,
      "net_gex": 2791679.6
    },
    {
      "strike": 522.5,
      "call_oi": 4.0,
      "put_oi": 2.0,
      "call_gex": 19356.22,
      "put_gex": -10319.75,
      "net_gex": 9036.47
    },
    {
      "strike": 523.0,
      "call_oi": 1587.0,
      "put_oi": 1396.0,
      "call_gex": 11437678.67,
      "put_gex": -9743448.37,
      "net_gex": 1694230.3
    },
    {
      "strike": 524.0,
      "call_oi": 1822.0,
      "put_oi": 1051.0,
      "call_gex": 11441582.0,
      "put_gex": -4680889.01,
      "net_gex": 6760692.99
    },
    {
      "strike": 525.0,
      "call_oi": 11159.0,
      "put_oi": 2017.0,
      "call_gex": 56934998.04,
      "put_gex": -7442224.27,
      "net_gex": 49492773.77
    },
    {
      "strike": 526.0,
      "call_oi": 1828.0,
      "put_oi": 56.0,
      "call_gex": 5095817.83,
      "put_gex": -130734.66,
      "net_gex": 4965083.17
    },
    {
      "strike": 527.0,
      "call_oi": 426.0,
      "put_oi": 102.0,
      "call_gex": 1925996.92,
      "put_gex": -591487.45,
      "net_gex": 1334509.47
    },
    {
      "strike": 528.0,
      "call_oi": 627.0,
      "put_oi": 62.0,
      "call_gex": 2147523.99,
      "put_gex": -117661.19,
      "net_gex": 2029862.8
    },
    {
      "strike": 529.0,
      "call_oi": 1049.0,
      "put_oi": 44.0,
      "call_gex": 5122980.7,
      "put_gex": -29221.47,
      "net_gex": 5093759.23
    },
    {
      "strike": 530.0,
      "call_oi": 8646.0,
      "put_oi": 503.0,
      "call_gex": 26798600.23,
      "put_gex": -1477649.22,
      "net_gex": 25320951.01
    },
    {
      "strike": 531.0,
      "call_oi": 1520.0,
      "put_oi": 23.0,
      "call_gex": 1520345.18,
      "put_gex": -43123.72,
      "net_gex": 1477221.46
    },
    {
      "strike": 532.0,
      "call_oi": 95.0,
      "put_oi": 36.0,
      "call_gex": 54486.14,
      "put_gex": -5854.99,
      "net_gex": 48631.15
    },
    {
      "strike": 533.0,
      "call_oi": 1256.0,
      "put_oi": 16.0,
      "call_gex": 99026.83,
      "put_gex": -427.76,
      "net_gex": 98599.06
    },
    {
      "strike": 534.0,
      "call_oi": 191.0,
      "put_oi": 16.0,
      "call_gex": 21013.79,
      "put_gex": -427.76,
      "net_gex": 20586.03
    },
    {
      "strike": 535.0,
      "call_oi": 7870.0,
      "put_oi": 1013.0,
      "call_gex": 23727886.35,
      "put_gex": -2309511.99,
      "net_gex": 21418374.36
    },
    {
      "strike": 536.0,
      "call_oi": 0.0,
      "put_oi": 0.0,
      "call_gex": 0.0,
      "put_gex": 0.0,
      "net_gex": 0.0
    },
    {
      "strike": 537.0,
      "call_oi": 2.0,
      "put_oi": 0.0,
      "call_gex": 4277.62,
      "put_gex": 0.0,
      "net_gex": 4277.62
    },
    {
      "strike": 538.0,
      "call_oi": 0.0,
      "put_oi": 0.0,
      "call_gex": 0.0,
      "put_gex": 0.0,
      "net_gex": 0.0
    },
    {
      "strike": 539.0,
      "call_oi": 0.0,
      "put_oi": 0.0,
      "call_gex": 0.0,
      "put_gex": 0.0,
      "net_gex": 0.0
    },
    {
      "strike": 540.0,
      "call_oi": 5229.0,
      "put_oi": 80.0,
      "call_gex": 9194763.83,
      "put_gex": -215645.35,
      "net_gex": 8979118.47
    },
    {
      "strike": 541.0,
      "call_oi": 2.0,
      "put_oi": 0.0,
      "call_gex": 2459.63,
      "put_gex": 0.0,
      "net_gex": 2459.63
    },
    {
      "strike": 542.0,
      "call_oi": 0.0,
      "put_oi": 0.0,
      "call_gex": 0.0,
      "put_gex": 0.0,
      "net_gex": 0.0
    },
    {
      "strike": 543.0,
      "call_oi": 0.0,
      "put_oi": 0.0,
      "call_gex": 0.0,
      "put_gex": 0.0,
      "net_gex": 0.0
    },
    {
      "strike": 544.0,
      "call_oi": 0.0,
      "put_oi": 0.0,
      "call_gex": 0.0,
      "put_gex": 0.0,
      "net_gex": 0.0
    },
    {
      "strike": 545.0,
      "call_oi": 11204.0,
      "put_oi": 36.0,
      "call_gex": 23296274.83,
      "put_gex": -113303.37,
      "net_gex": 23182971.45
    },
    {
      "strike": 550.0,
      "call_oi": 8484.0,
      "put_oi": 243.0,
      "call_gex": 11762082.43,
      "put_gex": -539407.47,
      "net_gex": 11222674.96
    },
    {
      "strike": 555.0,
      "call_oi": 4930.0,
      "put_oi": 18.0,
      "call_gex": 5089000.38,
      "put_gex": -29970.05,
      "net_gex": 5059030.33
    },
    {
      "strike": 560.0,
      "call_oi": 3903.0,
      "put_oi": 10.0,
      "call_gex": 5838679.44,
      "put_gex": -14196.34,
      "net_gex": 5824483.1
    },
    {
      "strike": 565.0,
      "call_oi": 2196.0,
      "put_oi": 0.0,
      "call_gex": 3180728.84,
      "put_gex": 0.0,
      "net_gex": 3180728.84
    },
    {
      "strike": 570.0,
      "call_oi": 2399.0,
      "put_oi": 18.0,
      "call_gex": 2546946.45,
      "put_gex": -29168.0,
      "net_gex": 2517778.45
    },
    {
      "strike": 575.0,
      "call_oi": 3517.0,
      "put_oi": 9.0,
      "call_gex": 4016387.99,
      "put_gex": -16442.09,
      "net_gex": 3999945.9
    },
    {
      "strike": 580.0,
      "call_oi": 1519.0,
      "put_oi": 22.0,
      "call_gex": 999759.23,
      "put_gex": -32429.68,
      "net_gex": 967329.55
    },
    {
      "strike": 585.0,
      "call_oi": 804.0,
      "put_oi": 2.0,
      "call_gex": 835819.57,
      "put_gex": -3315.15,
      "net_gex": 832504.41
    },
    {
      "strike": 590.0,
      "call_oi": 2464.0,
      "put_oi": 4.0,
      "call_gex": 454352.53,
      "put_gex": -6309.48,
      "net_gex": 448043.05
    },
    {
      "strike": 595.0,
      "call_oi": 837.0,
      "put_oi": 0.0,
      "call_gex": 511716.7,
      "put_gex": 0.0,
      "net_gex": 511716.7
    },
    {
      "strike": 600.0,
      "call_oi": 2709.0,
      "put_oi": 2.0,
      "call_gex": 1867154.96,
      "put_gex": -427.76,
      "net_gex": 1866727.2
    },
    {
      "strike": 605.0,
      "call_oi": 3023.0,
      "put_oi": 0.0,
      "call_gex": 909856.15,
      "put_gex": 0.0,
      "net_gex": 909856.15
    },
    {
      "strike": 610.0,
      "call_oi": 375.0,
      "put_oi": 0.0,
      "call_gex": 286279.11,
      "put_gex": 0.0,
      "net_gex": 286279.11
    },
    {
      "strike": 615.0,
      "call_oi": 355.0,
      "put_oi": 0.0,
      "call_gex": 241506.61,
      "put_gex": 0.0,
      "net_gex": 241506.61
    },
    {
      "strike": 620.0,
      "call_oi": 387.0,
      "put_oi": 0.0,
      "call_gex": 345604.69,
      "put_gex": 0.0,
      "net_gex": 345604.69
    },
    {
      "strike": 625.0,
      "call_oi": 616.0,
      "put_oi": 0.0,
      "call_gex": 483343.95,
      "put_gex": 0.0,
      "net_gex": 483343.95
    },
    {
      "strike": 630.0,
      "call_oi": 422.0,
      "put_oi": 0.0,
      "call_gex": 328868.52,
      "put_gex": 0.0,
      "net_gex": 328868.52
    },
    {
      "strike": 635.0,
      "call_oi": 865.0,
      "put_oi": 0.0,
      "call_gex": 464816.52,
      "put_gex": 0.0,
      "net_gex": 464816.52
    },
    {
      "strike": 640.0,
      "call_oi": 687.0,
      "put_oi": 0.0,
      "call_gex": 428510.25,
      "put_gex": 0.0,
      "net_gex": 428510.25
    },
    {
      "strike": 645.0,
      "call_oi": 3107.0,
      "put_oi": 0.0,
      "call_gex": 1245508.31,
      "put_gex": 0.0,
      "net_gex": 1245508.31
    },
    {
      "strike": 650.0,
      "call_oi": 8721.0,
      "put_oi": 0.0,
      "call_gex": 3002218.54,
      "put_gex": 0.0,
      "net_gex": 3002218.54
    },
    {
      "strike": 655.0,
      "call_oi": 439.0,
      "put_oi": 0.0,
      "call_gex": 274542.79,
      "put_gex": 0.0,
      "net_gex": 274542.79
    },
    {
      "strike": 660.0,
      "call_oi": 282.0,
      "put_oi": 0.0,
      "call_gex": 115361.98,
      "put_gex": 0.0,
      "net_gex": 115361.98
    },
    {
      "strike": 665.0,
      "call_oi": 416.0,
      "put_oi": 0.0,
      "call_gex": 150384.96,
      "put_gex": 0.0,
      "net_gex": 150384.96
    },
    {
      "strike": 670.0,
      "call_oi": 7968.0,
      "put_oi": 0.0,
      "call_gex": 1786519.88,
      "put_gex": 0.0,
      "net_gex": 1786519.88
    },
    {
      "strike": 675.0,
      "call_oi": 7141.0,
      "put_oi": 0.0,
      "call_gex": 1396695.32,
      "put_gex": 0.0,
      "net_gex": 1396695.32
    },
    {
      "strike": 680.0,
      "call_oi": 43.0,
      "put_oi": 0.0,
      "call_gex": 24088.33,
      "put_gex": 0.0,
      "net_gex": 24088.33
    },
    {
      "strike": 685.0,
      "call_oi": 7.0,
      "put_oi": 0.0,
      "call_gex": 3609.24,
      "put_gex": 0.0,
      "net_gex": 3609.24
    },
    {
      "strike": 690.0,
      "call_oi": 2018.0,
      "put_oi": 0.0,
      "call_gex": 422976.09,
      "put_gex": 0.0,
      "net_gex": 422976.09
    },
    {
      "strike": 695.0,
      "call_oi": 39.0,
      "put_oi": 0.0,
      "call_gex": 14944.92,
      "put_gex": 0.0,
      "net_gex": 14944.92
    },
    {
      "strike": 700.0,
      "call_oi": 1196.0,
      "put_oi": 0.0,
      "call_gex": 412362.25,
      "put_gex": 0.0,
      "net_gex": 412362.25
    },
    {
      "strike": 705.0,
      "call_oi": 2.0,
      "put_oi": 0.0,
      "call_gex": 962.46,
      "put_gex": 0.0,
      "net_gex": 962.46
    },
    {
      "strike": 710.0,
      "call_oi": 3.0,
      "put_oi": 0.0,
      "call_gex": 1470.43,
      "put_gex": 0.0,
      "net_gex": 1470.43
    },
    {
      "strike": 715.0,
      "call_oi": 98.0,
      "put_oi": 0.0,
      "call_gex": 39327.34,
      "put_gex": 0.0,
      "net_gex": 39327.34
    },
    {
      "strike": 720.0,
      "call_oi": 11.0,
      "put_oi": 0.0,
      "call_gex": 4865.79,
      "put_gex": 0.0,
      "net_gex": 4865.79
    },
    {
      "strike": 725.0,
      "call_oi": 152.0,
      "put_oi": 0.0,
      "call_gex": 57079.45,
      "put_gex": 0.0,
      "net_gex": 57079.45
    },
    {
      "strike": 730.0,
      "call_oi": 170.0,
      "put_oi": 0.0,
      "call_gex": 90819.15,
      "put_gex": 0.0,
      "net_gex": 90819.15
    },
    {
      "strike": 735.0,
      "call_oi": 2.0,
      "put_oi": 0.0,
      "call_gex": 882.26,
      "put_gex": 0.0,
      "net_gex": 882.26
    },
    {
      "strike": 740.0,
      "call_oi": 173.0,
      "put_oi": 0.0,
      "call_gex": 87878.29,
      "put_gex": 0.0,
      "net_gex": 87878.29
    },
    {
      "strike": 745.0,
      "call_oi": 1.0,
      "put_oi": 0.0,
      "call_gex": 481.23,
      "put_gex": 0.0,
      "net_gex": 481.23
    },
    {
      "strike": 750.0,
      "call_oi": 141.0,
      "put_oi": 0.0,
      "call_gex": 67853.69,
      "put_gex": 0.0,
      "net_gex": 67853.69
    },
    {
      "strike": 755.0,
      "call_oi": 205.0,
      "put_oi": 0.0,
      "call_gex": 77852.62,
      "put_gex": 0.0,
      "net_gex": 77852.62
    },
    {
      "strike": 760.0,
      "call_oi": 2.0,
      "put_oi": 0.0,
      "call_gex": 908.99,
      "put_gex": 0.0,
      "net_gex": 908.99
    },
    {
      "strike": 765.0,
      "call_oi": 0.0,
      "put_oi": 0.0,
      "call_gex": 0.0,
      "put_gex": 0.0,
      "net_gex": 0.0
    },
    {
      "strike": 770.0,
      "call_oi": 0.0,
      "put_oi": 0.0,
      "call_gex": 0.0,
      "put_gex": 0.0,
      "net_gex": 0.0
    },
    {
      "strike": 775.0,
      "call_oi": 0.0,
      "put_oi": 0.0,
      "call_gex": 0.0,
      "put_gex": 0.0,
      "net_gex": 0.0
    }
  ],
  "source": "CBOE delayed quotes",
  "sign_convention": "calls positive, puts negative"
}