{
  "contract": "corn",
  "name": "Corn",
  "date": "2026-07-01",
  "curve_months": [
    {
      "expiry": "2026-07",
      "price": 421.5
    },
    {
      "expiry": "2026-09",
      "price": 423.5
    },
    {
      "expiry": "2026-12",
      "price": 443.0
    },
    {
      "expiry": "2027-03",
      "price": 458.25
    },
    {
      "expiry": "2027-05",
      "price": 467.25
    },
    {
      "expiry": "2027-07",
      "price": 473.5
    },
    {
      "expiry": "2027-09",
      "price": 466.25
    },
    {
      "expiry": "2027-12",
      "price": 473.5
    }
  ],
  "m1_price": 421.5,
  "m2_price": 423.5,
  "m3_price": 443.0,
  "m6_price": 473.5,
  "spread_m1m3": 5.1008,
  "spread_m1m6": 12.3369,
  "curve_slope_proxy": 0.9239,
  "signal": "CONTANGO",
  "source": "yfinance futures"
}