{
  "contract": "crude_oil",
  "name": "Crude Oil WTI",
  "date": "2026-07-01",
  "curve_months": [
    {
      "expiry": "2026-08",
      "price": 68.13999938964844
    },
    {
      "expiry": "2026-09",
      "price": 68.05999755859375
    },
    {
      "expiry": "2026-10",
      "price": 67.98999786376953
    },
    {
      "expiry": "2026-11",
      "price": 67.88999938964844
    },
    {
      "expiry": "2026-12",
      "price": 67.69999694824219
    },
    {
      "expiry": "2027-01",
      "price": 67.48999786376953
    },
    {
      "expiry": "2027-02",
      "price": 67.26000213623047
    }
  ],
  "m1_price": 68.13999938964844,
  "m2_price": 68.05999755859375,
  "m3_price": 67.98999786376953,
  "m6_price": 67.48999786376953,
  "spread_m1m3": -0.2201,
  "spread_m1m6": -0.9539,
  "curve_slope_proxy": -0.9734,
  "signal": "BACKWARDATION",
  "source": "yfinance futures"
}